Metadata-Version: 1.1
Name: cryptocompy
Version: 0.1.dev1
Summary: Simple wrapper for the public Cryptocompare API.
Home-page: https://github.com/ttsteiger/cryptocompare-python
Author: Titian Steiger
Author-email: titian.steiger@gmail.com
License: MIT
Download-URL: https://github.com/ttsteiger/cryptocompare-python/archive/0.1.dev1.tar.gz
Platform: UNKNOWN
